{
  "shops": [
    {
      "name": "ТД Достык",
      "description": "Кондитерский супермаркет Конфетка в торговом доме Достык - самый крупный магазин в своем классе. Огромный выбор и т.д.",
      "address": "Ауэзова 238",
      "image": "shop_images/Dostyq.jpg",
      "openingHours": "09:00 - 21:00",
      "mapUrl": "https://2gis.kz/kokshetau/firm/70000001034884916?m=69.391027%2C53.288215%2F19.79"
    },
    {
      "name": "ТД Доssстык",
      "description": "Кондитерский супермаркет Конфетка в торговом доме Достык - самый крупный магазин в своем классе. Огромный выбор и т.д.",
      "address": "Ауэзова 238",
      "image": "shop_images/Dostyq.jpg",
      "openingHours": "09:00 - 21:00",
      "mapUrl": "https://2gis.kz/kokshetau/firm/70000001034884916?m=69.391027%2C53.288215%2F19.79"
    }
  ]
}
